<?xml version = '1.0' encoding = 'UTF-8'?>
<FKIndexAssociation class="oracle.dbtools.crest.model.design.relational.FKIndexAssociation" directorySegmentName="seg_0" id="0056909C-3E54-6D54-CD0F-30D042346828" containerWithKeyObject="E0DA7609-8B0F-387D-E184-F4A69B6314CB" localFKIndex="3F9EEA47-58C3-1598-8809-AE4A65FC3B74" name="SYS_C008545">
<sourceConnName>로컬-TEAMPROJECT01</sourceConnName>
<sourceObjSchema>TEAMPROJECT01</sourceObjSchema>
<sourceObjName>SYS_C008545</sourceObjName>
<createdBy>USER</createdBy>
<createdTime>2024-11-08 08:20:43 UTC</createdTime>
<ownerDesignName>TEAMPROJECT01</ownerDesignName>
<referredTableLongName>TEAMPROJECT01.COMPANY</referredTableLongName>
<deleteRule>NO ACTION</deleteRule>
<referredTableID>2435EF69-1021-0712-65C7-8DA73AE253B6</referredTableID>
<keyObject>2C2413EA-BAB0-7CF2-B204-F8D826F4CE37</keyObject>
<referredKeyID>2C2413EA-BAB0-7CF2-B204-F8D826F4CE37</referredKeyID>
<mandatory>false</mandatory>
<refColNames>CODE</refColNames>
<transferable>true</transferable>
<rely>false</rely>
<columnDependencyConstraintGenerateInDDL>true</columnDependencyConstraintGenerateInDDL>
</FKIndexAssociation>
